langchain_prompty-0.1.2.dist-info/METADATA
langchain_prompty-0.1.2.dist-info/WHEEL
langchain_prompty-0.1.2.dist-info/entry_points.txt
langchain_prompty-0.1.2.dist-info/licenses/LICENSE
langchain_prompty/__init__.py
langchain_prompty/core.py
langchain_prompty/langchain.py
langchain_prompty/parsers.py
langchain_prompty/renderers.py
langchain_prompty/utils.py
langchain_prompty-0.1.2.dist-info/RECORD
