Metadata-Version: 2.1
Name: langchain-prompty
Version: 0.1.2
Summary: An integration package connecting Prompty and LangChain
License: MIT
Project-URL: Source Code, https://github.com/langchain-ai/langchain/tree/master/libs/partners/prompty
Project-URL: Release Notes, https://github.com/langchain-ai/langchain/releases?q=tag%3A%22langchain-prompty%3D%3D0%22&expanded=true
Project-URL: repository, https://github.com/langchain-ai/langchain
Requires-Python: >=3.9
Requires-Dist: langchain-core<1.0.0,>=0.3.76
Requires-Dist: pyyaml<7.0.0,>=6.0.1
